{
  "timestamp": "2026-06-07T11:47:32.229035",
  "totalPairs": 298,
  "upCount": 275,
  "downCount": 19,
  "totalVolume": 1142985529.2288125,
  "sentiment": "bullish",
  "btc": {
    "price": 62717.8,
    "change24h": 3.12,
    "volume": 369217758.786875
  },
  "eth": {
    "price": 1633.2,
    "change24h": 4.56,
    "volume": 221112990.7181452
  },
  "volatile": [
    {
      "symbol": "ZEUS-USDT",
      "price": 0.002909,
      "change": 53.83,
      "volume": 326011.7061032926
    },
    {
      "symbol": "JTO-USDT",
      "price": 0.6456,
      "change": 26.86,
      "volume": 3205973.85822353
    },
    {
      "symbol": "ALLO-USDT",
      "price": 0.3084,
      "change": -24.71,
      "volume": 27539032.7076023
    },
    {
      "symbol": "DASH-USDT",
      "price": 38.1,
      "change": 21.49,
      "volume": 1224066.872145
    },
    {
      "symbol": "OMI-USDT",
      "price": 0.000203,
      "change": 18.17,
      "volume": 52120.5699605898
    },
    {
      "symbol": "MEME-USDT",
      "price": 0.000636,
      "change": 15.97,
      "volume": 782590.67486931
    },
    {
      "symbol": "ID-USDT",
      "price": 0.02711,
      "change": 13.96,
      "volume": 142336.1110949
    },
    {
      "symbol": "ZEC-USDT",
      "price": 415.04,
      "change": 11.9,
      "volume": 39473879.0687709
    },
    {
      "symbol": "BASED-USDT",
      "price": 0.06846,
      "change": 11.83,
      "volume": 1996272.7956601
    },
    {
      "symbol": "ZEN-USDT",
      "price": 4.513,
      "change": 11.13,
      "volume": 239973.389537
    },
    {
      "symbol": "HUMA-USDT",
      "price": 0.0252,
      "change": 10.87,
      "volume": 252579.471952
    },
    {
      "symbol": "MON-USDT",
      "price": 0.02303,
      "change": 10.51,
      "volume": 1632936.304802
    },
    {
      "symbol": "CC-USDT",
      "price": 0.17027,
      "change": 10.32,
      "volume": 3074186.6451006
    },
    {
      "symbol": "TON-USDT",
      "price": 1.712,
      "change": 10.24,
      "volume": 7724358.4670254
    },
    {
      "symbol": "ZBCN-USDT",
      "price": 0.002725,
      "change": 10.23,
      "volume": 465155.5086301
    },
    {
      "symbol": "BIO-USDT",
      "price": 0.0288,
      "change": 10.05,
      "volume": 762467.90612296
    },
    {
      "symbol": "RESOLV-USDT",
      "price": 0.01784,
      "change": 9.38,
      "volume": 631193.9419755
    },
    {
      "symbol": "XCH-USDT",
      "price": 2.239,
      "change": 9.11,
      "volume": 216749.86889041
    },
    {
      "symbol": "ZKJ-USDT",
      "price": 0.007969,
      "change": 9.07,
      "volume": 579803.0596503641
    },
    {
      "symbol": "FET-USDT",
      "price": 0.2095,
      "change": 8.77,
      "volume": 901783.4738521
    }
  ],
  "sideways": [
    {
      "symbol": "PYUSD-USDT",
      "price": 1.0,
      "change": 0.01,
      "volume": 14509.67764878,
      "vola_7d": 0.76,
      "position_7d": 7.9
    },
    {
      "symbol": "AUDM-USDT",
      "price": 0.7034,
      "change": 0.0,
      "volume": 0.0,
      "vola_7d": 2.16,
      "position_7d": 0.0
    },
    {
      "symbol": "XAUT-USDT",
      "price": 4305.2,
      "change": 0.4,
      "volume": 3877272.1937989,
      "vola_7d": 5.77,
      "position_7d": 10.1
    },
    {
      "symbol": "TRX-USDT",
      "price": 0.32896,
      "change": 2.66,
      "volume": 18056674.500970308,
      "vola_7d": 10.88,
      "position_7d": 30.9
    },
    {
      "symbol": "ZENT-USDT",
      "price": 0.002717,
      "change": 0.3,
      "volume": 25806.730072,
      "vola_7d": 11.52,
      "position_7d": 8.1
    },
    {
      "symbol": "WLFI-USDT",
      "price": 0.05669,
      "change": 1.92,
      "volume": 1209746.8998131,
      "vola_7d": 18.43,
      "position_7d": 28.5
    }
  ],
  "topVolume": [
    {
      "symbol": "BTC-USDT",
      "price": 62717.8,
      "change": 3.12,
      "volume": 369217758.786875
    },
    {
      "symbol": "ETH-USDT",
      "price": 1633.2,
      "change": 4.56,
      "volume": 221112990.7181452
    },
    {
      "symbol": "SOL-USDT",
      "price": 65.17,
      "change": 4.37,
      "volume": 50474990.25063293
    },
    {
      "symbol": "USDC-USDT",
      "price": 1.0002,
      "change": 0.0,
      "volume": 42437861.46423007
    },
    {
      "symbol": "WLD-USDT",
      "price": 0.4334,
      "change": 2.46,
      "volume": 39952845.5133419
    },
    {
      "symbol": "ZEC-USDT",
      "price": 415.04,
      "change": 11.9,
      "volume": 39473879.0687709
    },
    {
      "symbol": "DOGE-USDT",
      "price": 0.08475,
      "change": 4.28,
      "volume": 35431232.19976882
    },
    {
      "symbol": "XRP-USDT",
      "price": 1.1402,
      "change": 5.02,
      "volume": 33034300.91853582
    },
    {
      "symbol": "HYPE-USDT",
      "price": 59.35,
      "change": -0.43,
      "volume": 31022875.8306245
    },
    {
      "symbol": "ALLO-USDT",
      "price": 0.3084,
      "change": -24.71,
      "volume": 27539032.7076023
    }
  ]
}