{
  "timestamp": "2026-07-07T08:14:05.729034",
  "totalPairs": 302,
  "upCount": 120,
  "downCount": 178,
  "totalVolume": 3654471356.488365,
  "sentiment": "bearish",
  "btc": {
    "price": 63123.4,
    "change24h": 0.16,
    "volume": 572353143.1966134
  },
  "eth": {
    "price": 1772.47,
    "change24h": -0.01,
    "volume": 2098609268.44987
  },
  "volatile": [
    {
      "symbol": "BLUR-USDT",
      "price": 0.01991,
      "change": 32.82,
      "volume": 5393520.381635514
    },
    {
      "symbol": "EDGE-USDT",
      "price": 0.3167,
      "change": 20.19,
      "volume": 4085028.9539677
    },
    {
      "symbol": "POR-USDT",
      "price": 0.1025,
      "change": -19.23,
      "volume": 352836.47391133
    },
    {
      "symbol": "ALLO-USDT",
      "price": 0.42054,
      "change": 18.17,
      "volume": 5047820.0235077
    },
    {
      "symbol": "CHIP-USDT",
      "price": 0.03591,
      "change": 16.14,
      "volume": 294044.0357787
    },
    {
      "symbol": "YFI-USDT",
      "price": 2313.0,
      "change": 15.71,
      "volume": 4216973.881444
    },
    {
      "symbol": "HMSTR-USDT",
      "price": 0.000317,
      "change": 14.87,
      "volume": 7855039.13262526
    },
    {
      "symbol": "MON-USDT",
      "price": 0.02499,
      "change": 13.08,
      "volume": 82202617.530392
    },
    {
      "symbol": "ZEUS-USDT",
      "price": 0.003469,
      "change": 11.62,
      "volume": 947722.1119493874
    },
    {
      "symbol": "BONK-USDT",
      "price": 4e-06,
      "change": -11.19,
      "volume": 6619588.624855398
    },
    {
      "symbol": "CATI-USDT",
      "price": 0.043,
      "change": -10.23,
      "volume": 112654.8820852
    },
    {
      "symbol": "NES-USDT",
      "price": 0.2649,
      "change": -8.84,
      "volume": 237935245.759432
    },
    {
      "symbol": "JTO-USDT",
      "price": 0.7862,
      "change": 8.08,
      "volume": 2628113.00948049
    },
    {
      "symbol": "RE-USDT",
      "price": 0.65999,
      "change": 6.88,
      "volume": 47722825.9404009
    },
    {
      "symbol": "EGLD-USDT",
      "price": 2.896,
      "change": 6.82,
      "volume": 96968.335215002
    },
    {
      "symbol": "LDO-USDT",
      "price": 0.2881,
      "change": 6.7,
      "volume": 709768.95897616
    },
    {
      "symbol": "VINE-USDT",
      "price": 0.009105,
      "change": -6.64,
      "volume": 104440.23839265
    },
    {
      "symbol": "ZRO-USDT",
      "price": 1.0135,
      "change": 6.38,
      "volume": 1808295.4792741
    },
    {
      "symbol": "CELO-USDT",
      "price": 0.07117,
      "change": 6.3,
      "volume": 347716.6212576198
    },
    {
      "symbol": "GODS-USDT",
      "price": 0.02532,
      "change": -6.26,
      "volume": 93959.19084063335
    }
  ],
  "sideways": [
    {
      "symbol": "PYUSD-USDT",
      "price": 1.0005,
      "change": 0.0,
      "volume": 43975.96118681,
      "vola_7d": 0.22,
      "position_7d": 27.3
    },
    {
      "symbol": "OKB-USDT",
      "price": 79.29,
      "change": -1.04,
      "volume": 7725450.74952197,
      "vola_7d": 5.12,
      "position_7d": 32.1
    },
    {
      "symbol": "KAIA-USDT",
      "price": 0.03482,
      "change": -1.05,
      "volume": 88586.5121073,
      "vola_7d": 6.72,
      "position_7d": 34.6
    },
    {
      "symbol": "PI-USDT",
      "price": 0.1119,
      "change": -0.44,
      "volume": 2488723.5027374,
      "vola_7d": 7.59,
      "position_7d": 15.5
    },
    {
      "symbol": "NAVX-USDT",
      "price": 0.007051,
      "change": 0.96,
      "volume": 85515.77035546,
      "vola_7d": 8.76,
      "position_7d": 41.4
    },
    {
      "symbol": "ETC-USDT",
      "price": 7.035,
      "change": -0.99,
      "volume": 1570269.68321754,
      "vola_7d": 9.27,
      "position_7d": 43.1
    },
    {
      "symbol": "IOST-USDT",
      "price": 0.000712,
      "change": -0.22,
      "volume": 62793.626532089074,
      "vola_7d": 9.82,
      "position_7d": 44.0
    },
    {
      "symbol": "CHZ-USDT",
      "price": 0.01785,
      "change": 0.17,
      "volume": 739153.598265027,
      "vola_7d": 10.11,
      "position_7d": 36.8
    },
    {
      "symbol": "SATS-USDT",
      "price": 0.0,
      "change": 0.93,
      "volume": 413133.3378793479,
      "vola_7d": 10.78,
      "position_7d": 42.3
    },
    {
      "symbol": "KNC-USDT",
      "price": 0.1104,
      "change": -0.18,
      "volume": 6878.886111679,
      "vola_7d": 10.95,
      "position_7d": 47.0
    },
    {
      "symbol": "CFX-USDT",
      "price": 0.04393,
      "change": -1.83,
      "volume": 292482.2642753134,
      "vola_7d": 11.16,
      "position_7d": 42.9
    },
    {
      "symbol": "APE-USDT",
      "price": 0.13561,
      "change": -2.11,
      "volume": 458103.6754891905,
      "vola_7d": 12.37,
      "position_7d": 15.0
    },
    {
      "symbol": "BABY-USDT",
      "price": 0.01353,
      "change": -2.31,
      "volume": 112355.117175,
      "vola_7d": 12.49,
      "position_7d": 34.6
    },
    {
      "symbol": "SAHARA-USDT",
      "price": 0.01047,
      "change": -0.76,
      "volume": 74401.401319,
      "vola_7d": 12.84,
      "position_7d": 45.7
    },
    {
      "symbol": "CFG-USDT",
      "price": 0.1933,
      "change": -0.85,
      "volume": 187883.12058470387,
      "vola_7d": 12.96,
      "position_7d": 37.1
    }
  ],
  "topVolume": [
    {
      "symbol": "ETH-USDT",
      "price": 1772.47,
      "change": -0.01,
      "volume": 2098609268.44987
    },
    {
      "symbol": "BTC-USDT",
      "price": 63123.4,
      "change": 0.16,
      "volume": 572353143.1966134
    },
    {
      "symbol": "NES-USDT",
      "price": 0.2649,
      "change": -8.84,
      "volume": 237935245.759432
    },
    {
      "symbol": "USDC-USDT",
      "price": 1.0007,
      "change": -0.02,
      "volume": 118516366.32335493
    },
    {
      "symbol": "MON-USDT",
      "price": 0.02499,
      "change": 13.08,
      "volume": 82202617.530392
    },
    {
      "symbol": "SOL-USDT",
      "price": 81.44,
      "change": 0.77,
      "volume": 75536042.03270885
    },
    {
      "symbol": "RE-USDT",
      "price": 0.65999,
      "change": 6.88,
      "volume": 47722825.9404009
    },
    {
      "symbol": "HYPE-USDT",
      "price": 70.753,
      "change": -0.02,
      "volume": 31565854.9080428
    },
    {
      "symbol": "XRP-USDT",
      "price": 1.126,
      "change": -1.81,
      "volume": 31486213.520041328
    },
    {
      "symbol": "DOGE-USDT",
      "price": 0.07488,
      "change": -2.77,
      "volume": 30953102.467492215
    }
  ]
}