{
  "timestamp": "2026-07-12T20:00:29.053035",
  "totalPairs": 303,
  "upCount": 51,
  "downCount": 248,
  "totalVolume": 1141874059.243611,
  "sentiment": "bearish",
  "btc": {
    "price": 64232.7,
    "change24h": -0.09,
    "volume": 154238803.5960565
  },
  "eth": {
    "price": 1821.34,
    "change24h": -0.17,
    "volume": 130622469.32663937
  },
  "volatile": [
    {
      "symbol": "LAT-USDT",
      "price": 0.000669,
      "change": 53.92,
      "volume": 1687663.1632982376
    },
    {
      "symbol": "AGLD-USDT",
      "price": 0.1892,
      "change": 22.78,
      "volume": 2012337.0241114043
    },
    {
      "symbol": "T-USDT",
      "price": 0.00542,
      "change": 18.03,
      "volume": 1497510.2125834248
    },
    {
      "symbol": "NES-USDT",
      "price": 0.2378,
      "change": -13.59,
      "volume": 1758896.182552
    },
    {
      "symbol": "ASP-USDT",
      "price": 0.0183,
      "change": -13.23,
      "volume": 124331.0432373
    },
    {
      "symbol": "ZEUS-USDT",
      "price": 0.002849,
      "change": 12.25,
      "volume": 328196.6836970475
    },
    {
      "symbol": "CARDS-USDT",
      "price": 0.1405,
      "change": -9.41,
      "volume": 634388.449228
    },
    {
      "symbol": "MMT-USDT",
      "price": 0.1716,
      "change": -7.59,
      "volume": 659637.487373
    },
    {
      "symbol": "MOODENG-USDT",
      "price": 0.03993,
      "change": -7.44,
      "volume": 607594.2904497
    },
    {
      "symbol": "EDGE-USDT",
      "price": 0.3995,
      "change": 7.16,
      "volume": 2524040.9406652
    },
    {
      "symbol": "VINE-USDT",
      "price": 0.009241,
      "change": -6.63,
      "volume": 141850.51045911
    },
    {
      "symbol": "OL-USDT",
      "price": 0.005186,
      "change": -6.51,
      "volume": 324392.0849341
    },
    {
      "symbol": "WLD-USDT",
      "price": 0.4387,
      "change": 6.48,
      "volume": 7449614.8061798
    },
    {
      "symbol": "PROMPT-USDT",
      "price": 0.02119,
      "change": -6.36,
      "volume": 59308.175883
    },
    {
      "symbol": "ARG-USDT",
      "price": 0.157,
      "change": -6.27,
      "volume": 106929.39784324
    },
    {
      "symbol": "UMA-USDT",
      "price": 0.3733,
      "change": -5.87,
      "volume": 59929.7692298358
    },
    {
      "symbol": "PARTI-USDT",
      "price": 0.03122,
      "change": -5.77,
      "volume": 481712.7325109
    },
    {
      "symbol": "SKL-USDT",
      "price": 0.004451,
      "change": -5.76,
      "volume": 306730.3529989271
    },
    {
      "symbol": "LDO-USDT",
      "price": 0.3092,
      "change": -5.67,
      "volume": 624035.09228056
    },
    {
      "symbol": "KAT-USDT",
      "price": 0.005149,
      "change": -5.66,
      "volume": 545637.5286057
    }
  ],
  "sideways": [
    {
      "symbol": "PYUSD-USDT",
      "price": 1.0003,
      "change": -0.01,
      "volume": 34940.31192501,
      "vola_7d": 0.09,
      "position_7d": 11.1
    },
    {
      "symbol": "AUDM-USDT",
      "price": 0.6941,
      "change": 0.0,
      "volume": 0.0,
      "vola_7d": 0.4,
      "position_7d": 3.6
    },
    {
      "symbol": "ETC-USDT",
      "price": 6.916,
      "change": -2.41,
      "volume": 681377.188726393,
      "vola_7d": 5.63,
      "position_7d": 26.0
    },
    {
      "symbol": "KNC-USDT",
      "price": 0.1098,
      "change": -3.09,
      "volume": 8322.8106838568,
      "vola_7d": 6.26,
      "position_7d": 40.3
    },
    {
      "symbol": "WLFI-USDT",
      "price": 0.05779,
      "change": -1.28,
      "volume": 1080627.2917118,
      "vola_7d": 8.32,
      "position_7d": 19.2
    },
    {
      "symbol": "LPT-USDT",
      "price": 1.548,
      "change": -2.89,
      "volume": 35625.712911392,
      "vola_7d": 8.59,
      "position_7d": 26.9
    },
    {
      "symbol": "ICX-USDT",
      "price": 0.02441,
      "change": -3.17,
      "volume": 13123.714117902,
      "vola_7d": 8.6,
      "position_7d": 34.3
    },
    {
      "symbol": "ENS-USDT",
      "price": 4.142,
      "change": -1.64,
      "volume": 98088.693828249,
      "vola_7d": 8.64,
      "position_7d": 46.2
    },
    {
      "symbol": "SONIC-USDT",
      "price": 0.02429,
      "change": -2.84,
      "volume": 7657.0360508,
      "vola_7d": 8.67,
      "position_7d": 31.2
    },
    {
      "symbol": "NAVX-USDT",
      "price": 0.007022,
      "change": -0.65,
      "volume": 13685.76366596,
      "vola_7d": 8.82,
      "position_7d": 37.0
    },
    {
      "symbol": "STRK-USDT",
      "price": 0.03026,
      "change": -3.75,
      "volume": 628649.217604067,
      "vola_7d": 8.94,
      "position_7d": 33.1
    },
    {
      "symbol": "APT-USDT",
      "price": 0.6214,
      "change": -3.81,
      "volume": 558503.54956166,
      "vola_7d": 9.52,
      "position_7d": 47.2
    },
    {
      "symbol": "SAND-USDT",
      "price": 0.04832,
      "change": -2.78,
      "volume": 123487.69824514382,
      "vola_7d": 9.96,
      "position_7d": 34.6
    },
    {
      "symbol": "LINEA-USDT",
      "price": 0.002398,
      "change": -2.24,
      "volume": 175178.831346,
      "vola_7d": 10.33,
      "position_7d": 23.1
    },
    {
      "symbol": "DOGE-USDT",
      "price": 0.07367,
      "change": -2.24,
      "volume": 14371982.891554656,
      "vola_7d": 10.41,
      "position_7d": 36.0
    }
  ],
  "topVolume": [
    {
      "symbol": "SLX-USDT",
      "price": 0.1516,
      "change": -5.19,
      "volume": 442825358.132272
    },
    {
      "symbol": "BTC-USDT",
      "price": 64232.7,
      "change": -0.09,
      "volume": 154238803.5960565
    },
    {
      "symbol": "TAO-USDT",
      "price": 212.9,
      "change": -0.56,
      "volume": 151307940.442359
    },
    {
      "symbol": "ETH-USDT",
      "price": 1821.34,
      "change": -0.17,
      "volume": 130622469.32663937
    },
    {
      "symbol": "SOL-USDT",
      "price": 77.69,
      "change": -0.58,
      "volume": 34571804.39464215
    },
    {
      "symbol": "USDC-USDT",
      "price": 1.0005,
      "change": 0.0,
      "volume": 17034832.883175567
    },
    {
      "symbol": "ZEC-USDT",
      "price": 538.74,
      "change": 4.53,
      "volume": 15764143.4035514
    },
    {
      "symbol": "DOGE-USDT",
      "price": 0.07367,
      "change": -2.24,
      "volume": 14371982.891554656
    },
    {
      "symbol": "HYPE-USDT",
      "price": 68.249,
      "change": 0.99,
      "volume": 12225968.2631227
    },
    {
      "symbol": "XRP-USDT",
      "price": 1.1005,
      "change": -1.35,
      "volume": 12044300.608132001
    }
  ]
}