{
  "timestamp": "2026-06-13T19:06:58.818368",
  "totalPairs": 298,
  "upCount": 214,
  "downCount": 76,
  "totalVolume": 821127359.6621666,
  "sentiment": "bullish",
  "btc": {
    "price": 64172.8,
    "change24h": 0.78,
    "volume": 302814340.0298559
  },
  "eth": {
    "price": 1678.32,
    "change24h": 0.63,
    "volume": 96430790.01151974
  },
  "volatile": [
    {
      "symbol": "MEGA-USDT",
      "price": 0.05688,
      "change": 19.67,
      "volume": 3576552.5137167
    },
    {
      "symbol": "HMSTR-USDT",
      "price": 0.000179,
      "change": -15.86,
      "volume": 2450882.13984442
    },
    {
      "symbol": "NOT-USDT",
      "price": 0.000498,
      "change": 15.25,
      "volume": 1981752.72439387
    },
    {
      "symbol": "ICP-USDT",
      "price": 2.59,
      "change": 13.8,
      "volume": 4057887.743788904
    },
    {
      "symbol": "MMT-USDT",
      "price": 0.1305,
      "change": 12.5,
      "volume": 673153.402941
    },
    {
      "symbol": "ALLO-USDT",
      "price": 0.37522,
      "change": -12.34,
      "volume": 8299968.5147584
    },
    {
      "symbol": "OL-USDT",
      "price": 0.006729,
      "change": 11.81,
      "volume": 470371.6329237
    },
    {
      "symbol": "GODS-USDT",
      "price": 0.02898,
      "change": 10.74,
      "volume": 47591.89323236354
    },
    {
      "symbol": "ENJ-USDT",
      "price": 0.0315,
      "change": -10.59,
      "volume": 569850.51168815
    },
    {
      "symbol": "CHIP-USDT",
      "price": 0.03374,
      "change": 9.83,
      "volume": 393098.4737753
    },
    {
      "symbol": "TRUMP-USDT",
      "price": 2.208,
      "change": 8.98,
      "volume": 22465717.9971925
    },
    {
      "symbol": "FET-USDT",
      "price": 0.2059,
      "change": 8.77,
      "volume": 1541596.6040917
    },
    {
      "symbol": "AR-USDT",
      "price": 2.046,
      "change": 8.6,
      "volume": 631554.437753158
    },
    {
      "symbol": "AIXBT-USDT",
      "price": 0.02411,
      "change": 8.41,
      "volume": 392164.28576133
    },
    {
      "symbol": "PHA-USDT",
      "price": 0.03574,
      "change": 8.3,
      "volume": 347227.61076317786
    },
    {
      "symbol": "WLD-USDT",
      "price": 0.5017,
      "change": 7.96,
      "volume": 22008491.6375885
    },
    {
      "symbol": "OP-USDT",
      "price": 0.1081,
      "change": 7.74,
      "volume": 2619968.93194762
    },
    {
      "symbol": "CETUS-USDT",
      "price": 0.01933,
      "change": 7.69,
      "volume": 33188.762451047
    },
    {
      "symbol": "DGB-USDT",
      "price": 0.00258,
      "change": 7.68,
      "volume": 7240.90776401267
    },
    {
      "symbol": "LINEA-USDT",
      "price": 0.00259,
      "change": 7.47,
      "volume": 394028.931791
    }
  ],
  "sideways": [
    {
      "symbol": "PYUSD-USDT",
      "price": 1.0001,
      "change": -0.04,
      "volume": 43241.65301236,
      "vola_7d": 0.17,
      "position_7d": 11.8
    },
    {
      "symbol": "TRX-USDT",
      "price": 0.31759,
      "change": 0.8,
      "volume": 11521936.615180133,
      "vola_7d": 5.76,
      "position_7d": 39.0
    },
    {
      "symbol": "ZENT-USDT",
      "price": 0.002606,
      "change": -1.4,
      "volume": 19775.4578303,
      "vola_7d": 7.78,
      "position_7d": 37.6
    },
    {
      "symbol": "LDO-USDT",
      "price": 0.2635,
      "change": -0.08,
      "volume": 244161.51115964,
      "vola_7d": 11.81,
      "position_7d": 43.2
    },
    {
      "symbol": "SD-USDT",
      "price": 0.143,
      "change": 2.44,
      "volume": 72604.9115985736,
      "vola_7d": 12.5,
      "position_7d": 41.8
    },
    {
      "symbol": "IRYS-USDT",
      "price": 0.01829,
      "change": 2.93,
      "volume": 493147.955372,
      "vola_7d": 18.64,
      "position_7d": 41.6
    },
    {
      "symbol": "ZEC-USDT",
      "price": 414.55,
      "change": -0.42,
      "volume": 15106265.9411379,
      "vola_7d": 20.01,
      "position_7d": 16.0
    },
    {
      "symbol": "ICX-USDT",
      "price": 0.0289,
      "change": -0.14,
      "volume": 298911.6365322545,
      "vola_7d": 21.1,
      "position_7d": 21.8
    }
  ],
  "topVolume": [
    {
      "symbol": "BTC-USDT",
      "price": 64172.8,
      "change": 0.78,
      "volume": 302814340.0298559
    },
    {
      "symbol": "ETH-USDT",
      "price": 1678.32,
      "change": 0.63,
      "volume": 96430790.01151974
    },
    {
      "symbol": "HYPE-USDT",
      "price": 59.864,
      "change": -1.9,
      "volume": 44418553.4716847
    },
    {
      "symbol": "SOL-USDT",
      "price": 68.12,
      "change": 1.58,
      "volume": 34069789.19054667
    },
    {
      "symbol": "USDC-USDT",
      "price": 1.0003,
      "change": 0.0,
      "volume": 28027265.366993457
    },
    {
      "symbol": "DOGE-USDT",
      "price": 0.08763,
      "change": -0.15,
      "volume": 25625917.679532032
    },
    {
      "symbol": "NIGHT-USDT",
      "price": 0.032542,
      "change": -3.31,
      "volume": 24106175.266834
    },
    {
      "symbol": "TRUMP-USDT",
      "price": 2.208,
      "change": 8.98,
      "volume": 22465717.9971925
    },
    {
      "symbol": "WLD-USDT",
      "price": 0.5017,
      "change": 7.96,
      "volume": 22008491.6375885
    },
    {
      "symbol": "ZEC-USDT",
      "price": 414.55,
      "change": -0.42,
      "volume": 15106265.9411379
    }
  ]
}