{
  "timestamp": "2026-07-12T11:03:57.059407",
  "totalPairs": 303,
  "upCount": 83,
  "downCount": 213,
  "totalVolume": 1331549864.2333586,
  "sentiment": "bearish",
  "btc": {
    "price": 63889.0,
    "change24h": -0.47,
    "volume": 221474390.46556267
  },
  "eth": {
    "price": 1800.02,
    "change24h": 0.1,
    "volume": 163533942.79943347
  },
  "volatile": [
    {
      "symbol": "T-USDT",
      "price": 0.006067,
      "change": 53.56,
      "volume": 2074038.1217948012
    },
    {
      "symbol": "LAT-USDT",
      "price": 0.000626,
      "change": 42.98,
      "volume": 1234450.3147080436
    },
    {
      "symbol": "PARTI-USDT",
      "price": 0.03239,
      "change": -13.65,
      "volume": 1422959.851852
    },
    {
      "symbol": "HMSTR-USDT",
      "price": 0.000205,
      "change": -12.37,
      "volume": 2412607.91562565
    },
    {
      "symbol": "NES-USDT",
      "price": 0.2434,
      "change": -9.99,
      "volume": 1741395.105393
    },
    {
      "symbol": "ALLO-USDT",
      "price": 0.35711,
      "change": -9.18,
      "volume": 2748721.8179232
    },
    {
      "symbol": "ZEUS-USDT",
      "price": 0.002482,
      "change": -8.28,
      "volume": 58512.4566954235
    },
    {
      "symbol": "MMT-USDT",
      "price": 0.1753,
      "change": -8.03,
      "volume": 812316.441879
    },
    {
      "symbol": "EGLD-USDT",
      "price": 3.066,
      "change": 8.0,
      "volume": 89294.40020601
    },
    {
      "symbol": "ARG-USDT",
      "price": 0.1603,
      "change": -6.96,
      "volume": 86522.77302519
    },
    {
      "symbol": "RPL-USDT",
      "price": 1.854,
      "change": 6.8,
      "volume": 37048.4212277
    },
    {
      "symbol": "CARDS-USDT",
      "price": 0.1462,
      "change": -6.52,
      "volume": 405497.406581
    },
    {
      "symbol": "SLX-USDT",
      "price": 0.157,
      "change": -6.49,
      "volume": 512791299.468426
    },
    {
      "symbol": "JTO-USDT",
      "price": 0.5931,
      "change": -6.16,
      "volume": 631601.0002112
    },
    {
      "symbol": "OMI-USDT",
      "price": 0.000168,
      "change": 6.05,
      "volume": 60024.3465783468
    },
    {
      "symbol": "MORPHO-USDT",
      "price": 1.9882,
      "change": -5.83,
      "volume": 689131.4318045
    },
    {
      "symbol": "ETHFI-USDT",
      "price": 0.4376,
      "change": 5.67,
      "volume": 952455.30070789
    },
    {
      "symbol": "WLD-USDT",
      "price": 0.4179,
      "change": 5.32,
      "volume": 6905790.7184375
    },
    {
      "symbol": "SKL-USDT",
      "price": 0.00466,
      "change": -5.3,
      "volume": 444458.57879750425
    },
    {
      "symbol": "GRASS-USDT",
      "price": 0.3959,
      "change": -5.06,
      "volume": 533562.899414
    }
  ],
  "sideways": [
    {
      "symbol": "PYUSD-USDT",
      "price": 1.0003,
      "change": -0.02,
      "volume": 39146.08294758,
      "vola_7d": 0.12,
      "position_7d": 33.3
    },
    {
      "symbol": "AUDM-USDT",
      "price": 0.6941,
      "change": 0.0,
      "volume": 0.0,
      "vola_7d": 0.49,
      "position_7d": 20.6
    },
    {
      "symbol": "XAUT-USDT",
      "price": 4095.7,
      "change": -0.35,
      "volume": 1438212.1014374,
      "vola_7d": 4.26,
      "position_7d": 44.2
    },
    {
      "symbol": "ETC-USDT",
      "price": 6.871,
      "change": -2.92,
      "volume": 669841.754739513,
      "vola_7d": 6.73,
      "position_7d": 12.0
    },
    {
      "symbol": "KAIA-USDT",
      "price": 0.03466,
      "change": -0.23,
      "volume": 135298.8555709,
      "vola_7d": 6.73,
      "position_7d": 40.5
    },
    {
      "symbol": "WLFI-USDT",
      "price": 0.05771,
      "change": -0.59,
      "volume": 1023229.7177724,
      "vola_7d": 8.32,
      "position_7d": 17.5
    },
    {
      "symbol": "ICX-USDT",
      "price": 0.02459,
      "change": -1.32,
      "volume": 11893.01027872806,
      "vola_7d": 8.6,
      "position_7d": 43.1
    },
    {
      "symbol": "NAVX-USDT",
      "price": 0.007062,
      "change": 0.48,
      "volume": 33712.56679091,
      "vola_7d": 8.82,
      "position_7d": 43.7
    },
    {
      "symbol": "LPT-USDT",
      "price": 1.547,
      "change": -3.07,
      "volume": 35958.409920736,
      "vola_7d": 9.39,
      "position_7d": 23.9
    },
    {
      "symbol": "CFX-USDT",
      "price": 0.04346,
      "change": 0.56,
      "volume": 331169.9398951276,
      "vola_7d": 9.51,
      "position_7d": 43.6
    },
    {
      "symbol": "APT-USDT",
      "price": 0.6208,
      "change": -2.07,
      "volume": 667764.78440653,
      "vola_7d": 9.52,
      "position_7d": 46.1
    },
    {
      "symbol": "SONIC-USDT",
      "price": 0.02464,
      "change": -0.32,
      "volume": 7852.4913475,
      "vola_7d": 9.56,
      "position_7d": 43.8
    },
    {
      "symbol": "STRK-USDT",
      "price": 0.03046,
      "change": -1.36,
      "volume": 752821.765538617,
      "vola_7d": 9.96,
      "position_7d": 35.8
    },
    {
      "symbol": "LINEA-USDT",
      "price": 0.002389,
      "change": -2.21,
      "volume": 173730.7654711,
      "vola_7d": 10.33,
      "position_7d": 19.4
    },
    {
      "symbol": "SAND-USDT",
      "price": 0.04873,
      "change": -1.54,
      "volume": 150650.7663103644,
      "vola_7d": 10.36,
      "position_7d": 42.8
    }
  ],
  "topVolume": [
    {
      "symbol": "SLX-USDT",
      "price": 0.157,
      "change": -6.49,
      "volume": 512791299.468426
    },
    {
      "symbol": "BTC-USDT",
      "price": 63889.0,
      "change": -0.47,
      "volume": 221474390.46556267
    },
    {
      "symbol": "ETH-USDT",
      "price": 1800.02,
      "change": 0.1,
      "volume": 163533942.79943347
    },
    {
      "symbol": "TAO-USDT",
      "price": 210.1,
      "change": -1.04,
      "volume": 145748387.825462
    },
    {
      "symbol": "SOL-USDT",
      "price": 76.74,
      "change": -1.65,
      "volume": 36041259.33160331
    },
    {
      "symbol": "USDC-USDT",
      "price": 1.0004,
      "change": -0.04,
      "volume": 31146942.99072559
    },
    {
      "symbol": "DOGE-USDT",
      "price": 0.07305,
      "change": -1.97,
      "volume": 16068382.410496978
    },
    {
      "symbol": "ZEC-USDT",
      "price": 521.45,
      "change": 3.52,
      "volume": 14297910.8717614
    },
    {
      "symbol": "XRP-USDT",
      "price": 1.0947,
      "change": -1.34,
      "volume": 12611022.08874357
    },
    {
      "symbol": "HYPE-USDT",
      "price": 66.858,
      "change": 0.09,
      "volume": 11755892.9241745
    }
  ]
}