{
  "timestamp": "2026-06-23T10:53:57.363754",
  "totalPairs": 299,
  "upCount": 23,
  "downCount": 272,
  "totalVolume": 1295628067.6045063,
  "sentiment": "bearish",
  "btc": {
    "price": 62276.3,
    "change24h": -2.95,
    "volume": 389279439.03394073
  },
  "eth": {
    "price": 1651.63,
    "change24h": -5.61,
    "volume": 282840103.8538103
  },
  "volatile": [
    {
      "symbol": "BICO-USDT",
      "price": 0.02771,
      "change": -30.69,
      "volume": 5593934.7370350845
    },
    {
      "symbol": "RESOLV-USDT",
      "price": 0.02769,
      "change": 30.24,
      "volume": 7122564.9229798
    },
    {
      "symbol": "W-USDT",
      "price": 0.01047,
      "change": -15.22,
      "volume": 2245300.6207713755
    },
    {
      "symbol": "MMT-USDT",
      "price": 0.2006,
      "change": 14.24,
      "volume": 2034926.426539
    },
    {
      "symbol": "EIGEN-USDT",
      "price": 0.26,
      "change": -13.62,
      "volume": 1867810.6808678
    },
    {
      "symbol": "TNSR-USDT",
      "price": 0.035,
      "change": -12.83,
      "volume": 1176011.970004516
    },
    {
      "symbol": "IRYS-USDT",
      "price": 0.015,
      "change": -11.82,
      "volume": 617377.199455
    },
    {
      "symbol": "ENA-USDT",
      "price": 0.08457,
      "change": -11.74,
      "volume": 2785501.856068
    },
    {
      "symbol": "WLD-USDT",
      "price": 0.5567,
      "change": -11.41,
      "volume": 17591911.9764383
    },
    {
      "symbol": "OFC-USDT",
      "price": 0.0209,
      "change": -10.3,
      "volume": 811542.259696
    },
    {
      "symbol": "LIT-USDT",
      "price": 1.5291,
      "change": -10.01,
      "volume": 2898057.2083893
    },
    {
      "symbol": "SPK-USDT",
      "price": 0.01677,
      "change": -9.84,
      "volume": 314770.991998
    },
    {
      "symbol": "S-USDT",
      "price": 0.02446,
      "change": -9.77,
      "volume": 358468.34075723
    },
    {
      "symbol": "ARKM-USDT",
      "price": 0.1199,
      "change": -9.73,
      "volume": 141958.3147417
    },
    {
      "symbol": "ACT-USDT",
      "price": 0.008076,
      "change": -9.56,
      "volume": 372289.728470656
    },
    {
      "symbol": "BREV-USDT",
      "price": 0.08846,
      "change": 9.51,
      "volume": 1305999.9302921
    },
    {
      "symbol": "PENDLE-USDT",
      "price": 1.299,
      "change": -9.41,
      "volume": 314139.060078
    },
    {
      "symbol": "VELODROME-USDT",
      "price": 0.02146,
      "change": 9.38,
      "volume": 282251.675536164
    },
    {
      "symbol": "ZORA-USDT",
      "price": 0.007117,
      "change": -9.36,
      "volume": 51910.95619982
    },
    {
      "symbol": "SAHARA-USDT",
      "price": 0.01144,
      "change": -9.21,
      "volume": 390385.474213
    }
  ],
  "sideways": [
    {
      "symbol": "AUDM-USDT",
      "price": 0.698,
      "change": -0.46,
      "volume": 1396.0,
      "vola_7d": 1.0,
      "position_7d": 0.0
    },
    {
      "symbol": "ZENT-USDT",
      "price": 0.00249,
      "change": -0.76,
      "volume": 23747.2797186,
      "vola_7d": 4.86,
      "position_7d": 32.8
    },
    {
      "symbol": "XAUT-USDT",
      "price": 4113.3,
      "change": -1.93,
      "volume": 7800460.3059735,
      "vola_7d": 6.79,
      "position_7d": 10.9
    },
    {
      "symbol": "BTC-USDT",
      "price": 62276.3,
      "change": -2.95,
      "volume": 389279439.03394073,
      "vola_7d": 7.28,
      "position_7d": 8.0
    },
    {
      "symbol": "NAVX-USDT",
      "price": 0.006702,
      "change": -0.89,
      "volume": 118612.04253599,
      "vola_7d": 9.23,
      "position_7d": 33.7
    },
    {
      "symbol": "SEI-USDT",
      "price": 0.05261,
      "change": -4.28,
      "volume": 706909.2482934,
      "vola_7d": 9.42,
      "position_7d": 8.8
    },
    {
      "symbol": "PI-USDT",
      "price": 0.1291,
      "change": -4.79,
      "volume": 3337631.7801771,
      "vola_7d": 9.84,
      "position_7d": 16.8
    },
    {
      "symbol": "AAVE-USDT",
      "price": 72.14,
      "change": -4.94,
      "volume": 1389800.7396235,
      "vola_7d": 10.5,
      "position_7d": 20.9
    },
    {
      "symbol": "BNT-USDT",
      "price": 0.265,
      "change": -1.92,
      "volume": 3272.9323505587,
      "vola_7d": 10.76,
      "position_7d": 23.7
    },
    {
      "symbol": "PROVE-USDT",
      "price": 0.1968,
      "change": -6.51,
      "volume": 216559.3852316,
      "vola_7d": 11.1,
      "position_7d": 1.8
    },
    {
      "symbol": "RAY-USDT",
      "price": 0.5948,
      "change": -6.36,
      "volume": 158480.8328949239,
      "vola_7d": 11.82,
      "position_7d": 18.2
    },
    {
      "symbol": "WLFI-USDT",
      "price": 0.05752,
      "change": -2.34,
      "volume": 1200011.7702186,
      "vola_7d": 11.9,
      "position_7d": 14.4
    },
    {
      "symbol": "ETC-USDT",
      "price": 7.023,
      "change": -3.77,
      "volume": 985430.450998355,
      "vola_7d": 12.35,
      "position_7d": 12.8
    },
    {
      "symbol": "DOGE-USDT",
      "price": 0.07904,
      "change": -5.51,
      "volume": 27611927.376344956,
      "vola_7d": 12.43,
      "position_7d": 6.7
    },
    {
      "symbol": "BONK-USDT",
      "price": 4e-06,
      "change": -5.77,
      "volume": 948179.678751314,
      "vola_7d": 13.26,
      "position_7d": 9.3
    }
  ],
  "topVolume": [
    {
      "symbol": "BTC-USDT",
      "price": 62276.3,
      "change": -2.95,
      "volume": 389279439.03394073
    },
    {
      "symbol": "ETH-USDT",
      "price": 1651.63,
      "change": -5.61,
      "volume": 282840103.8538103
    },
    {
      "symbol": "SOL-USDT",
      "price": 68.74,
      "change": -6.94,
      "volume": 73911909.63760407
    },
    {
      "symbol": "USDC-USDT",
      "price": 1.0009,
      "change": 0.01,
      "volume": 71538307.3345858
    },
    {
      "symbol": "HYPE-USDT",
      "price": 62.473,
      "change": -7.6,
      "volume": 50729448.6079937
    },
    {
      "symbol": "USDG-USDT",
      "price": 1.0012,
      "change": 0.0,
      "volume": 27813616.132649
    },
    {
      "symbol": "DOGE-USDT",
      "price": 0.07904,
      "change": -5.51,
      "volume": 27611927.376344956
    },
    {
      "symbol": "XRP-USDT",
      "price": 1.1028,
      "change": -3.17,
      "volume": 26535669.94173849
    },
    {
      "symbol": "OKB-USDT",
      "price": 77.9,
      "change": 2.2,
      "volume": 24659252.21677615
    },
    {
      "symbol": "ZEC-USDT",
      "price": 420.99,
      "change": -7.03,
      "volume": 23638023.2646356
    }
  ]
}