{
  "timestamp": "2026-06-07T21:00:05.268428",
  "totalPairs": 298,
  "upCount": 245,
  "downCount": 44,
  "totalVolume": 1265958387.519966,
  "sentiment": "bullish",
  "btc": {
    "price": 61899.7,
    "change24h": 1.95,
    "volume": 409268063.16405964
  },
  "eth": {
    "price": 1628.81,
    "change24h": 4.57,
    "volume": 243494189.5862954
  },
  "volatile": [
    {
      "symbol": "ZEUS-USDT",
      "price": 0.002878,
      "change": 43.47,
      "volume": 637528.0734831537
    },
    {
      "symbol": "ALLO-USDT",
      "price": 0.31312,
      "change": -34.15,
      "volume": 17473565.3256016
    },
    {
      "symbol": "JTO-USDT",
      "price": 0.6077,
      "change": 20.84,
      "volume": 5492911.0611555
    },
    {
      "symbol": "ZEC-USDT",
      "price": 422.44,
      "change": 20.28,
      "volume": 42895681.1883749
    },
    {
      "symbol": "OMI-USDT",
      "price": 0.000216,
      "change": 18.51,
      "volume": 59282.100854931
    },
    {
      "symbol": "DASH-USDT",
      "price": 37.01,
      "change": 18.02,
      "volume": 2211196.09868
    },
    {
      "symbol": "OFC-USDT",
      "price": 0.04253,
      "change": 16.71,
      "volume": 1057700.803842
    },
    {
      "symbol": "WLD-USDT",
      "price": 0.4749,
      "change": 14.6,
      "volume": 52094305.819685
    },
    {
      "symbol": "SAHARA-USDT",
      "price": 0.03711,
      "change": 13.31,
      "volume": 601038.076477
    },
    {
      "symbol": "ZKJ-USDT",
      "price": 0.008596,
      "change": 13.19,
      "volume": 449766.7740010174
    },
    {
      "symbol": "DUCK-USDT",
      "price": 5.8e-05,
      "change": 11.41,
      "volume": 124026.380920364
    },
    {
      "symbol": "EIGEN-USDT",
      "price": 0.1751,
      "change": 9.16,
      "volume": 380256.1028794
    },
    {
      "symbol": "CATI-USDT",
      "price": 0.04246,
      "change": -8.69,
      "volume": 160362.1122813
    },
    {
      "symbol": "PRCL-USDT",
      "price": 0.00781,
      "change": -8.01,
      "volume": 100416.79491037
    },
    {
      "symbol": "KITE-USDT",
      "price": 0.19419,
      "change": 7.79,
      "volume": 759455.1983545
    },
    {
      "symbol": "NEAR-USDT",
      "price": 2.011,
      "change": 7.43,
      "volume": 13915510.601751987
    },
    {
      "symbol": "BIO-USDT",
      "price": 0.02752,
      "change": 7.37,
      "volume": 954471.44749737
    },
    {
      "symbol": "DEGEN-USDT",
      "price": 0.001597,
      "change": 7.27,
      "volume": 845123.456099
    },
    {
      "symbol": "PENGU-USDT",
      "price": 0.006693,
      "change": 7.21,
      "volume": 2670892.0963
    },
    {
      "symbol": "XCH-USDT",
      "price": 2.177,
      "change": 7.19,
      "volume": 233208.14330925
    }
  ],
  "sideways": [
    {
      "symbol": "PYUSD-USDT",
      "price": 1.0001,
      "change": 0.0,
      "volume": 13522.15211021,
      "vola_7d": 0.76,
      "position_7d": 9.2
    },
    {
      "symbol": "AUDM-USDT",
      "price": 0.7034,
      "change": 0.0,
      "volume": 0.0,
      "vola_7d": 2.06,
      "position_7d": 0.0
    },
    {
      "symbol": "XAUT-USDT",
      "price": 4299.6,
      "change": 0.28,
      "volume": 5517602.6460955,
      "vola_7d": 5.62,
      "position_7d": 7.9
    },
    {
      "symbol": "TRX-USDT",
      "price": 0.32608,
      "change": 1.07,
      "volume": 17249408.784577683,
      "vola_7d": 9.17,
      "position_7d": 27.4
    },
    {
      "symbol": "ZENT-USDT",
      "price": 0.002706,
      "change": 0.07,
      "volume": 28929.5454227,
      "vola_7d": 11.86,
      "position_7d": 7.5
    },
    {
      "symbol": "WLFI-USDT",
      "price": 0.05536,
      "change": -0.04,
      "volume": 1651870.905742,
      "vola_7d": 18.43,
      "position_7d": 14.9
    },
    {
      "symbol": "BTC-USDT",
      "price": 61899.7,
      "change": 1.95,
      "volume": 409268063.16405964,
      "vola_7d": 21.48,
      "position_7d": 21.7
    }
  ],
  "topVolume": [
    {
      "symbol": "BTC-USDT",
      "price": 61899.7,
      "change": 1.95,
      "volume": 409268063.16405964
    },
    {
      "symbol": "ETH-USDT",
      "price": 1628.81,
      "change": 4.57,
      "volume": 243494189.5862954
    },
    {
      "symbol": "SOL-USDT",
      "price": 64.73,
      "change": 4.67,
      "volume": 54403860.08210863
    },
    {
      "symbol": "WLD-USDT",
      "price": 0.4749,
      "change": 14.6,
      "volume": 52094305.819685
    },
    {
      "symbol": "ZEC-USDT",
      "price": 422.44,
      "change": 20.28,
      "volume": 42895681.1883749
    },
    {
      "symbol": "HYPE-USDT",
      "price": 58.475,
      "change": 3.49,
      "volume": 39178103.3186529
    },
    {
      "symbol": "DOGE-USDT",
      "price": 0.08421,
      "change": 4.12,
      "volume": 38427074.89217376
    },
    {
      "symbol": "XRP-USDT",
      "price": 1.133,
      "change": 4.43,
      "volume": 32509169.098016076
    },
    {
      "symbol": "NIGHT-USDT",
      "price": 0.028967,
      "change": -6.54,
      "volume": 31262709.8543195
    },
    {
      "symbol": "USDC-USDT",
      "price": 1.0002,
      "change": 0.0,
      "volume": 23564147.684905596
    }
  ]
}