{
  "timestamp": "2026-07-03T08:47:39.031616",
  "totalPairs": 302,
  "upCount": 248,
  "downCount": 51,
  "totalVolume": 1770244413.5183692,
  "sentiment": "bullish",
  "btc": {
    "price": 61791.8,
    "change24h": 2.06,
    "volume": 647308299.874768
  },
  "eth": {
    "price": 1727.16,
    "change24h": 6.27,
    "volume": 326686217.8949847
  },
  "volatile": [
    {
      "symbol": "ALLO-USDT",
      "price": 0.34561,
      "change": 30.24,
      "volume": 10576605.1610747
    },
    {
      "symbol": "BREV-USDT",
      "price": 0.08338,
      "change": -28.59,
      "volume": 5759935.5825103
    },
    {
      "symbol": "NES-USDT",
      "price": 0.2355,
      "change": 18.82,
      "volume": 191742024.250601
    },
    {
      "symbol": "RPL-USDT",
      "price": 1.713,
      "change": 15.35,
      "volume": 578362.4923416
    },
    {
      "symbol": "SKY-USDT",
      "price": 0.06019,
      "change": 13.46,
      "volume": 1012690.688315
    },
    {
      "symbol": "WLD-USDT",
      "price": 0.4213,
      "change": 13.31,
      "volume": 18680659.3416673
    },
    {
      "symbol": "UNI-USDT",
      "price": 3.22,
      "change": 13.06,
      "volume": 11125042.572928065
    },
    {
      "symbol": "S-USDT",
      "price": 0.0262,
      "change": 12.83,
      "volume": 614134.55750679
    },
    {
      "symbol": "SLP-USDT",
      "price": 0.000516,
      "change": 12.6,
      "volume": 186576.10507393745
    },
    {
      "symbol": "SNX-USDT",
      "price": 0.2344,
      "change": 9.79,
      "volume": 360865.4963812791
    },
    {
      "symbol": "PARTI-USDT",
      "price": 0.04914,
      "change": 9.74,
      "volume": 227720.1110453
    },
    {
      "symbol": "ID-USDT",
      "price": 0.0353,
      "change": 9.49,
      "volume": 399844.04807654
    },
    {
      "symbol": "BANANA-USDT",
      "price": 2.945,
      "change": 9.2,
      "volume": 53916.7793393
    },
    {
      "symbol": "RAY-USDT",
      "price": 0.7285,
      "change": 8.85,
      "volume": 745775.938884286
    },
    {
      "symbol": "MEGA-USDT",
      "price": 0.04964,
      "change": 8.67,
      "volume": 805412.1048912
    },
    {
      "symbol": "MANA-USDT",
      "price": 0.0692,
      "change": 8.58,
      "volume": 476850.2263416949
    },
    {
      "symbol": "CARDS-USDT",
      "price": 0.2398,
      "change": 7.92,
      "volume": 4664320.266179
    },
    {
      "symbol": "WET-USDT",
      "price": 0.06393,
      "change": -7.66,
      "volume": 459255.8687842
    },
    {
      "symbol": "ARKM-USDT",
      "price": 0.12115,
      "change": 7.57,
      "volume": 202635.03675099
    },
    {
      "symbol": "MOVE-USDT",
      "price": 0.01206,
      "change": 7.1,
      "volume": 727347.1613
    }
  ],
  "sideways": [
    {
      "symbol": "PYUSD-USDT",
      "price": 1.0012,
      "change": 0.04,
      "volume": 37292.2750986,
      "vola_7d": 0.15,
      "position_7d": 33.3
    },
    {
      "symbol": "WLFI-USDT",
      "price": 0.05741,
      "change": -1.59,
      "volume": 1074458.1032375,
      "vola_7d": 6.3,
      "position_7d": 21.6
    },
    {
      "symbol": "NAVX-USDT",
      "price": 0.006931,
      "change": -0.32,
      "volume": 9287.54138889,
      "vola_7d": 7.25,
      "position_7d": 6.2
    },
    {
      "symbol": "ZKJ-USDT",
      "price": 0.007076,
      "change": 1.24,
      "volume": 51628.9687625563,
      "vola_7d": 14.09,
      "position_7d": 31.3
    },
    {
      "symbol": "SEI-USDT",
      "price": 0.04963,
      "change": 4.09,
      "volume": 917330.0613255,
      "vola_7d": 16.07,
      "position_7d": 42.2
    },
    {
      "symbol": "ASP-USDT",
      "price": 0.02374,
      "change": -1.21,
      "volume": 49502.3794784,
      "vola_7d": 16.15,
      "position_7d": 31.5
    },
    {
      "symbol": "AAVE-USDT",
      "price": 86.6,
      "change": 1.7,
      "volume": 2213493.05146775,
      "vola_7d": 19.81,
      "position_7d": 23.2
    },
    {
      "symbol": "PI-USDT",
      "price": 0.1186,
      "change": 2.33,
      "volume": 2044628.6172011,
      "vola_7d": 20.92,
      "position_7d": 33.2
    },
    {
      "symbol": "SAHARA-USDT",
      "price": 0.01076,
      "change": 1.8,
      "volume": 142279.454631,
      "vola_7d": 21.13,
      "position_7d": 41.6
    }
  ],
  "topVolume": [
    {
      "symbol": "BTC-USDT",
      "price": 61791.8,
      "change": 2.06,
      "volume": 647308299.874768
    },
    {
      "symbol": "ETH-USDT",
      "price": 1727.16,
      "change": 6.27,
      "volume": 326686217.8949847
    },
    {
      "symbol": "NES-USDT",
      "price": 0.2355,
      "change": 18.82,
      "volume": 191742024.250601
    },
    {
      "symbol": "SOL-USDT",
      "price": 81.22,
      "change": 3.58,
      "volume": 106559274.14063457
    },
    {
      "symbol": "USDC-USDT",
      "price": 1.0009,
      "change": 0.0,
      "volume": 89720935.21725444
    },
    {
      "symbol": "HYPE-USDT",
      "price": 67.778,
      "change": 7.06,
      "volume": 34268284.1140063
    },
    {
      "symbol": "XRP-USDT",
      "price": 1.1044,
      "change": 3.75,
      "volume": 29041814.105079774
    },
    {
      "symbol": "DOGE-USDT",
      "price": 0.07531,
      "change": 3.05,
      "volume": 25593443.448167033
    },
    {
      "symbol": "ZEC-USDT",
      "price": 452.51,
      "change": 6.69,
      "volume": 18958558.4159003
    },
    {
      "symbol": "WLD-USDT",
      "price": 0.4213,
      "change": 13.31,
      "volume": 18680659.3416673
    }
  ]
}