{
  "timestamp": "2026-07-10T16:17:20.808940",
  "totalPairs": 303,
  "upCount": 208,
  "downCount": 92,
  "totalVolume": 1770088697.3992674,
  "sentiment": "bullish",
  "btc": {
    "price": 64138.5,
    "change24h": 2.07,
    "volume": 528381668.2161699
  },
  "eth": {
    "price": 1795.27,
    "change24h": 3.29,
    "volume": 201833280.11228085
  },
  "volatile": [
    {
      "symbol": "SKL-USDT",
      "price": 0.00532,
      "change": 49.23,
      "volume": 4357897.466272672
    },
    {
      "symbol": "CARDS-USDT",
      "price": 0.168,
      "change": 16.67,
      "volume": 985929.354889
    },
    {
      "symbol": "KAT-USDT",
      "price": 0.005624,
      "change": 15.36,
      "volume": 2251474.4254956
    },
    {
      "symbol": "PARTI-USDT",
      "price": 0.04324,
      "change": -15.07,
      "volume": 581543.4468418
    },
    {
      "symbol": "DORA-USDT",
      "price": 0.005145,
      "change": 14.9,
      "volume": 87787.98564942
    },
    {
      "symbol": "NES-USDT",
      "price": 0.2981,
      "change": 11.48,
      "volume": 3627568.996853
    },
    {
      "symbol": "AI-USDT",
      "price": 0.02841,
      "change": 9.73,
      "volume": 1056957.479486
    },
    {
      "symbol": "ALLO-USDT",
      "price": 0.40825,
      "change": -9.63,
      "volume": 2333057.8956025
    },
    {
      "symbol": "IOTA-USDT",
      "price": 0.04002,
      "change": 9.37,
      "volume": 1927695.8512760238
    },
    {
      "symbol": "KAITO-USDT",
      "price": 0.6143,
      "change": -9.21,
      "volume": 896885.1354617
    },
    {
      "symbol": "PEPE-USDT",
      "price": 3e-06,
      "change": 8.41,
      "volume": 5444183.410374614
    },
    {
      "symbol": "RVN-USDT",
      "price": 0.004036,
      "change": 8.06,
      "volume": 634052.5470665633
    },
    {
      "symbol": "ZEC-USDT",
      "price": 505.16,
      "change": 8.03,
      "volume": 11750767.3151308
    },
    {
      "symbol": "ACT-USDT",
      "price": 0.009415,
      "change": 7.86,
      "volume": 697774.876335998
    },
    {
      "symbol": "ZENT-USDT",
      "price": 0.001942,
      "change": -7.7,
      "volume": 137434.5404138
    },
    {
      "symbol": "GRASS-USDT",
      "price": 0.389,
      "change": 7.52,
      "volume": 718211.670262
    },
    {
      "symbol": "MORPHO-USDT",
      "price": 2.2611,
      "change": 7.3,
      "volume": 1469637.7905082
    },
    {
      "symbol": "CVX-USDT",
      "price": 1.25,
      "change": 6.93,
      "volume": 37201.412895973
    },
    {
      "symbol": "UNI-USDT",
      "price": 3.566,
      "change": 6.67,
      "volume": 7639127.013483533
    },
    {
      "symbol": "SENT-USDT",
      "price": 0.01476,
      "change": -5.93,
      "volume": 2534203.814263
    }
  ],
  "sideways": [
    {
      "symbol": "PYUSD-USDT",
      "price": 1.0004,
      "change": -0.04,
      "volume": 16736.41413301,
      "vola_7d": 0.12,
      "position_7d": 41.7
    },
    {
      "symbol": "BNT-USDT",
      "price": 0.2709,
      "change": 3.36,
      "volume": 1595.9399787899,
      "vola_7d": 8.55,
      "position_7d": 39.3
    },
    {
      "symbol": "KNC-USDT",
      "price": 0.1116,
      "change": 1.0,
      "volume": 5422.7134677021,
      "vola_7d": 8.78,
      "position_7d": 47.9
    },
    {
      "symbol": "NAVX-USDT",
      "price": 0.007021,
      "change": 1.89,
      "volume": 32334.98181585,
      "vola_7d": 8.82,
      "position_7d": 36.8
    },
    {
      "symbol": "WLFI-USDT",
      "price": 0.05886,
      "change": 1.48,
      "volume": 1333881.4632388,
      "vola_7d": 9.28,
      "position_7d": 46.7
    },
    {
      "symbol": "STRK-USDT",
      "price": 0.03067,
      "change": 0.79,
      "volume": 534154.050710978,
      "vola_7d": 9.96,
      "position_7d": 43.7
    },
    {
      "symbol": "BABY-USDT",
      "price": 0.01324,
      "change": -0.38,
      "volume": 91191.057471,
      "vola_7d": 9.96,
      "position_7d": 14.6
    },
    {
      "symbol": "ENS-USDT",
      "price": 4.157,
      "change": 1.02,
      "volume": 109686.505724809,
      "vola_7d": 10.97,
      "position_7d": 39.8
    },
    {
      "symbol": "SATS-USDT",
      "price": 0.0,
      "change": 2.11,
      "volume": 237337.78053940224,
      "vola_7d": 11.21,
      "position_7d": 44.5
    },
    {
      "symbol": "CFG-USDT",
      "price": 0.19246,
      "change": 1.12,
      "volume": 199475.37864926644,
      "vola_7d": 11.26,
      "position_7d": 36.4
    },
    {
      "symbol": "CFX-USDT",
      "price": 0.04323,
      "change": 1.81,
      "volume": 256623.6947611851,
      "vola_7d": 11.67,
      "position_7d": 30.8
    },
    {
      "symbol": "DOGE-USDT",
      "price": 0.0743,
      "change": 2.47,
      "volume": 19563501.43504919,
      "vola_7d": 11.8,
      "position_7d": 39.3
    },
    {
      "symbol": "IOST-USDT",
      "price": 0.000705,
      "change": 0.36,
      "volume": 50866.82428963875,
      "vola_7d": 12.15,
      "position_7d": 45.9
    },
    {
      "symbol": "AERGO-USDT",
      "price": 0.02321,
      "change": 1.0,
      "volume": 9986.64766970254,
      "vola_7d": 12.35,
      "position_7d": 40.7
    },
    {
      "symbol": "GAS-USDT",
      "price": 1.0521,
      "change": 1.8,
      "volume": 92188.6370712893,
      "vola_7d": 12.74,
      "position_7d": 37.0
    }
  ],
  "topVolume": [
    {
      "symbol": "BTC-USDT",
      "price": 64138.5,
      "change": 2.07,
      "volume": 528381668.2161699
    },
    {
      "symbol": "TAO-USDT",
      "price": 212.2,
      "change": 2.76,
      "volume": 260298502.165435
    },
    {
      "symbol": "SLX-USDT",
      "price": 0.1784,
      "change": 1.13,
      "volume": 206764493.919348
    },
    {
      "symbol": "ETH-USDT",
      "price": 1795.27,
      "change": 3.29,
      "volume": 201833280.11228085
    },
    {
      "symbol": "DATA-USDT",
      "price": 0.276,
      "change": 2.22,
      "volume": 151112288.575526
    },
    {
      "symbol": "USDC-USDT",
      "price": 1.0006,
      "change": 0.0,
      "volume": 82043995.98669638
    },
    {
      "symbol": "SOL-USDT",
      "price": 78.2,
      "change": 0.88,
      "volume": 53246947.76487113
    },
    {
      "symbol": "DOGE-USDT",
      "price": 0.0743,
      "change": 2.47,
      "volume": 19563501.43504919
    },
    {
      "symbol": "HYPE-USDT",
      "price": 67.847,
      "change": 0.36,
      "volume": 19424240.1708605
    },
    {
      "symbol": "XRP-USDT",
      "price": 1.1057,
      "change": 1.51,
      "volume": 18669683.301444262
    }
  ]
}