{
  "timestamp": "2026-05-24T23:50:33.471343",
  "totalPairs": 299,
  "upCount": 40,
  "downCount": 256,
  "totalVolume": 915588907.1627436,
  "sentiment": "bearish",
  "btc": {
    "price": 77138.8,
    "change24h": 0.56,
    "volume": 253963910.7178201
  },
  "eth": {
    "price": 2103.56,
    "change24h": -0.7,
    "volume": 147928891.46052578
  },
  "volatile": [
    {
      "symbol": "SD-USDT",
      "price": 0.1787,
      "change": 13.46,
      "volume": 459700.1640292971
    },
    {
      "symbol": "HUMA-USDT",
      "price": 0.02541,
      "change": 8.31,
      "volume": 580449.919148
    },
    {
      "symbol": "BICO-USDT",
      "price": 0.02787,
      "change": -7.84,
      "volume": 450984.9187565577
    },
    {
      "symbol": "HYPE-USDT",
      "price": 63.085,
      "change": 7.83,
      "volume": 71373517.6368822
    },
    {
      "symbol": "GMT-USDT",
      "price": 0.011811,
      "change": -7.76,
      "volume": 749436.5711709537
    },
    {
      "symbol": "FLUID-USDT",
      "price": 1.621,
      "change": -7.32,
      "volume": 21297.605358
    },
    {
      "symbol": "MORPHO-USDT",
      "price": 2.247,
      "change": 7.3,
      "volume": 545769.356147
    },
    {
      "symbol": "AI-USDT",
      "price": 0.03324,
      "change": -6.84,
      "volume": 67436881.777547
    },
    {
      "symbol": "XCH-USDT",
      "price": 2.747,
      "change": -6.44,
      "volume": 401372.546323479
    },
    {
      "symbol": "BREV-USDT",
      "price": 0.1098,
      "change": -6.31,
      "volume": 85588.908052
    },
    {
      "symbol": "OMI-USDT",
      "price": 0.00017,
      "change": 6.19,
      "volume": 132740.7169675972
    },
    {
      "symbol": "YB-USDT",
      "price": 0.13008,
      "change": 6.08,
      "volume": 420182.01422737
    },
    {
      "symbol": "PROS-USDT",
      "price": 0.6169,
      "change": -5.86,
      "volume": 958808.7196445
    },
    {
      "symbol": "PROVE-USDT",
      "price": 0.265,
      "change": -5.53,
      "volume": 347176.1017454
    },
    {
      "symbol": "SCR-USDT",
      "price": 0.04302,
      "change": -5.45,
      "volume": 17677.29851631
    },
    {
      "symbol": "BASED-USDT",
      "price": 0.06842,
      "change": -5.42,
      "volume": 1180924.3270819
    },
    {
      "symbol": "VELODROME-USDT",
      "price": 0.01606,
      "change": -5.42,
      "volume": 17096.271784065
    },
    {
      "symbol": "ARKM-USDT",
      "price": 0.13616,
      "change": -5.41,
      "volume": 611782.3381094
    },
    {
      "symbol": "ZEUS-USDT",
      "price": 0.004165,
      "change": -5.38,
      "volume": 112406.791825062
    },
    {
      "symbol": "LIT-USDT",
      "price": 1.2951,
      "change": 5.35,
      "volume": 8574117.8355068
    }
  ],
  "sideways": [],
  "topVolume": [
    {
      "symbol": "BTC-USDT",
      "price": 77138.8,
      "change": 0.56,
      "volume": 253963910.7178201
    },
    {
      "symbol": "ETH-USDT",
      "price": 2103.56,
      "change": -0.7,
      "volume": 147928891.46052578
    },
    {
      "symbol": "HYPE-USDT",
      "price": 63.085,
      "change": 7.83,
      "volume": 71373517.6368822
    },
    {
      "symbol": "AI-USDT",
      "price": 0.03324,
      "change": -6.84,
      "volume": 67436881.777547
    },
    {
      "symbol": "SOL-USDT",
      "price": 85.4,
      "change": -0.32,
      "volume": 44489269.92523693
    },
    {
      "symbol": "USDC-USDT",
      "price": 1.001,
      "change": 0.01,
      "volume": 29543053.083639294
    },
    {
      "symbol": "DOGE-USDT",
      "price": 0.10237,
      "change": -0.62,
      "volume": 23899672.174947653
    },
    {
      "symbol": "XAUT-USDT",
      "price": 4560.0,
      "change": 1.02,
      "volume": 21865708.4377318
    },
    {
      "symbol": "XRP-USDT",
      "price": 1.3524,
      "change": -0.47,
      "volume": 17794897.213837404
    },
    {
      "symbol": "ZEC-USDT",
      "price": 666.73,
      "change": 5.34,
      "volume": 15794224.0410601
    }
  ]
}